<?xml version="1.0" encoding="utf-8"?>
<Presentation>
  <PresentationID>4154045</PresentationID>
  <Title>How to click funny pictures of your dog</Title>
  <Description>Our furry friends are photogenic, that’s true. But, it takes a lot of effort, from the photographer’s end, to click good or super funny dog pictures that everybody loves.</Description>
  <CreatedDateTime>01/20/2020 00:05:29</CreatedDateTime>
  <ThumbnailURL>http://c.asstatic.com/images/4154045_637150755537237500-118_88.png</ThumbnailURL>
  <embed>&lt;object width="481" height="402" id="player"&gt;&lt;param name="movie" value="http://www.authorstream.com/player/player.swf?p=4154045_637150755537237500" /&gt;&lt;param name="allowfullscreen" value="true" /&gt;&lt;param name="allowScriptAccess" value="always"/&gt;&lt;embed src="http://www.authorstream.com/player/player.swf?p=4154045_637150755537237500" type="application/x-shockwave-flash" allowscriptaccess="always" allowfullscreen="true" width="481" height="402"&gt;&lt;/embed&gt;&lt;/object&gt;&lt;br&gt;&lt;font size='2'&gt;Uploaded on authorSTREAM by &lt;a href="http://www.authorstream.com/User-Presentations/flauntpet/" target="_blank" title="More presentations by flauntpet on authorSTREAM"&gt;flauntpet&lt;/a&gt;&lt;/font&gt;</embed>
  <PresentationUrl>http://www.authorstream.com/presentation/flauntpet-4154045-click-funny-pictures-dog</PresentationUrl>
  <PresentationViews>5</PresentationViews>
  <Category>Entertainment</Category>
  <Tags>Pet photo upload,Submit pet photos,Submit your dog photos,Upload pet photos,</Tags>
</Presentation>